prlps_translit/__init__.py
prlps_translit/mapping.py
prlps_translit-0.0.1.dist-info/LICENSE.txt
prlps_translit-0.0.1.dist-info/METADATA
prlps_translit-0.0.1.dist-info/WHEEL
prlps_translit-0.0.1.dist-info/top_level.txt
prlps_translit-0.0.1.dist-info/RECORD
