Metadata-Version: 2.1
Name: prlps-translit
Version: 0.0.1
Summary: веб поиск
Home-page: https://github.com/prolapser/prlps_translit
Author: prolapser
License: LICENSE.txt
Classifier: Development Status :: 4 - Beta
Classifier: Intended Audience :: Developers
Classifier: License :: OSI Approved :: MIT License
Classifier: Operating System :: OS Independent
Requires-Python: >=3.10
License-File: LICENSE.txt
